LICENSE
MANIFEST.in
README.md
requirements.txt
setup.py
nittymcpick/__init__.py
nittymcpick/__main__.py
nittymcpick.egg-info/PKG-INFO
nittymcpick.egg-info/SOURCES.txt
nittymcpick.egg-info/dependency_links.txt
nittymcpick.egg-info/entry_points.txt
nittymcpick.egg-info/requires.txt
nittymcpick.egg-info/top_level.txt
nittymcpick/cls/__init__.py
nittymcpick/cls/comment.py
nittymcpick/cls/difffile.py
nittymcpick/cls/job.py
nittymcpick/cls/linter.py